LICENSE.txt
MANIFEST
setup.py
src/tests/test_xmlobjects.py
src/xmlobjects/__init__.py
src/xmlobjects/elements_lib.py
src/xmlobjects/parser.py
src/xmlobjects/xmlobject.py
src/xmlobjects.egg-info/PKG-INFO
src/xmlobjects.egg-info/SOURCES.txt
src/xmlobjects.egg-info/dependency_links.txt
src/xmlobjects.egg-info/top_level.txt