Metadata-Version: 1.0
Name: xmlobjects
Version: 0.4
Summary: An Object Relation Mapper for XML
Home-page: http://code.google.com/p/xmlobjects/
Author: Open Source Applications Foundation
Author-email: tools-dev@osafoundation.org
License: http://www.apache.org/licenses/LICENSE-2.0
Platform: Any
Classifier: Development Status :: 4 - Beta
Classifier: Environment :: Console
Classifier: Intended Audience :: Developers
Classifier: License :: OSI Approved :: Apache Software License
Classifier: Operating System :: OS Independent
Classifier: Topic :: Software Development :: Libraries :: Python Modules
